rtl/pe.sv
module pe #(
    parameter int DATA_WIDTH = 8,
    parameter int ACC_WIDTH  = 32
)(
    input  logic                          clk,
    input  logic                          rst_n,  // active low reset (resets when reset is low)
    input  logic                          load_weight,
    input  logic signed [DATA_WIDTH-1:0]  weight_in,
    input  logic signed [DATA_WIDTH-1:0]  act_in,
    output logic signed [DATA_WIDTH-1:0]  act_out,
    input  logic signed [ACC_WIDTH-1:0]   psum_in,
    output logic signed [ACC_WIDTH-1:0]   psum_out
);


    logic signed [DATA_WIDTH-1:0] weight_reg;



    always_ff @(posedge clk) begin
        if (!rst_n) weight_reg <= 0;
        else if(load_weight) weight_reg <= weight_in;
        // else just keep weight_reg <= weight_reg
    end 


    // 2 stage design, multiply first, then add

    logic signed [(DATA_WIDTH*2)-1:0] prod_reg;
    logic signed [DATA_WIDTH-1:0] act_reg1, act_reg2;
    logic signed [ACC_WIDTH-1:0] psum_reg;

    always_ff @(posedge clk) begin
        if (!rst_n) begin
            prod_reg <= 0;
            act_reg1  <= 0;
            psum_reg <= 0;
        end else begin
            prod_reg <= weight_reg * act_in;
            act_reg1  <= act_in;
            psum_reg <= psum_in;
        end
    end

    logic signed [ACC_WIDTH-1:0] psum_out_reg;
    always_ff @(posedge clk) begin
        if (!rst_n) begin
            psum_out_reg <= 0;
            act_reg2 <= 0;
        end
        else begin
            psum_out_reg <= psum_reg + prod_reg;
            act_reg2 <= act_reg1;
        end
    end

    assign act_out = act_reg2;
    assign psum_out = psum_out_reg;



endmodule

tb/tb_pe.sv
// =============================================================================
// tb_pe.sv - Directed testbench for the single PE (Phase 1)
// =============================================================================
`timescale 1ns/1ps

module tb_pe;

    localparam int DATA_WIDTH = 8;
    localparam int ACC_WIDTH  = 32;
    localparam time CLK_PERIOD = 10ns;

    logic clk;
    logic rst_n;
    logic load_weight;
    logic signed [DATA_WIDTH-1:0] weight_in;
    logic signed [DATA_WIDTH-1:0] act_in;
    logic signed [DATA_WIDTH-1:0] act_out;
    logic signed [ACC_WIDTH-1:0]  psum_in;
    logic signed [ACC_WIDTH-1:0]  psum_out;

    int pass_count = 0;
    int fail_count = 0;

    int f_arr[4];
    int past_arr[6];

    pe #(
        .DATA_WIDTH(DATA_WIDTH),
        .ACC_WIDTH (ACC_WIDTH)
    ) dut (
        .clk        (clk),
        .rst_n      (rst_n),
        .load_weight(load_weight),
        .weight_in  (weight_in),
        .act_in     (act_in),
        .act_out    (act_out),
        .psum_in    (psum_in),
        .psum_out   (psum_out)
    );

    // Clock generation
   
    initial clk = 0;
    always #(CLK_PERIOD/2) clk = ~clk;

    // Reset task 
    task automatic apply_reset();
        rst_n       = 0; // remember active low reset
        load_weight = 0;
        weight_in   = '0;
        act_in      = '0;
        psum_in     = '0;
        repeat (3) @(posedge clk);
        rst_n = 1;
        @(posedge clk);
    endtask

    // Load a weight into the PE 
    task automatic load_pe_weight(input logic signed [DATA_WIDTH-1:0] w);
        @(negedge clk);
        load_weight = 1;
        weight_in   = w;
        @(negedge clk);
        load_weight = 0;
    endtask





    //   1. Drive act_in = act_val, psum_in = psum_val for one cycle
    //   2. Wait the correct number of cycles for YOUR pipeline latency
    //      (this is the part you need to get right - use @(posedge clk)
    //      or @(negedge clk) the right number of times)
    //   3. Compare psum_out against expected_psum_out
    //   4. Print [PASS] or [FAIL] with the test name, increment
    //      pass_count/fail_count accordingly

    task automatic apply_and_check(
        input  logic signed [DATA_WIDTH-1:0] act_val,
        input  logic signed [ACC_WIDTH-1:0]  psum_val,
        input  logic signed [ACC_WIDTH-1:0]  expected_psum_out,
        input  string                        test_name
    );

        // act_in and psum_in are the logic wires we hooked up to the DUT, and we
        // are assigning them the values of the params. in this task
        act_in  = act_val;
        psum_in = psum_val;
        @(negedge clk);
        act_in = 0;
        psum_in = 0;

        

        repeat(1)@(negedge clk); // TODO: adjust this to match YOUR pipeline latency
        if (psum_out !== expected_psum_out) begin
            $display("[FAIL] %s: psum_out = %0d, expected = %0d", test_name, psum_out, expected_psum_out);
            fail_count++;
        end else begin
            $display("[PASS] %s: psum_out = %0d", test_name, psum_out);
            pass_count++;
        end

        if (act_out !== act_val) begin
            $display("[FAIL] %s: act_out = %0d, expected = %0d", test_name, act_out, act_val);
            fail_count++;
        end else begin
            $display("[PASS] %s: act_out = %0d", test_name, act_out);
            pass_count++;
        end

    endtask

  
    initial begin
        $display("========================================");
        $display(" PE Directed Testbench - Phase 1");
        $display("========================================");

        apply_reset();

        $display("basic_positive_mac");
        load_pe_weight(5);
        apply_and_check(3,0,15,"basic_positive_mac");
        

        $display("accumulate_nonzero_psum");
        apply_and_check(4,100,120,"accumulate_nonzero_psum");

        $display("negative_activation");
        apply_and_check(-3,0,-15,"negative_activation");

        $display("negative_weight");
        load_pe_weight(-7);
        apply_and_check(6,0,-42, "negative_weight");

        $display("neg_times_neg");
        apply_and_check(-6,0,42,"neg_times_neg");

        $display("max_magnitude_operands");
        load_pe_weight(-128);
        apply_and_check(-128,0,16384,"max_magnitude_operands");

        $display("zero_weight_passthrough");
        load_pe_weight(0);
        apply_and_check(127,500,500,"zero_weight_passthrough");

        $display("zero_activation_passthrough");
        load_pe_weight(9);
        apply_and_check(0,77,77, "zero_activation_passthrough");
        

        // continous act_in flow checks

        repeat(5)@(negedge clk); // wait a few cycles to let the pipeline drain

        // int f_arr[4] = '{10,20,30,40};
        // int past_arr[6] = '{0,0,10,20,30,40};

        f_arr[0] = 10;
        f_arr[1] = 20;
        f_arr[2] = 30;
        f_arr[3] = 40;

        past_arr[0] = 0;
        past_arr[1] = 0;
        past_arr[2] = 10;
        past_arr[3] = 20;
        past_arr[4] = 30;
        past_arr[5] = 40;

        for (int i = 0; i < 6; i++) begin
            if (i < 4) act_in = f_arr[i];

            if (i > 1) begin
                if (act_out != past_arr[i]) begin
                    $display("[FAIL] continuous_act_in_flow: act_out = %0d, expected = %0d", act_out, past_arr[i]);
                    fail_count++;
                end else begin
                    $display("[PASS] continuous_act_in_flow: act_out = %0d", act_out);
                    pass_count++;
                end

            end



            @(negedge clk);
        end 




        // -------------------------------------------------------------------
        $display("========================================");
        $display(" RESULTS: %0d passed, %0d failed", pass_count, fail_count);
        $display("========================================");

        if (fail_count == 0)
            $display("ALL TESTS PASSED");
        else
            $display("SOME TESTS FAILED - see log above");

        $finish;
    end

    // -------------------------------------------------------------------
    // Waveform dump (given)
    // -------------------------------------------------------------------
    initial begin
        $dumpfile("pe_wave.vcd");
        $dumpvars(0, tb_pe);
    end

    // Safety timeout
    initial begin
        #10000;
        $display("[TIMEOUT] Testbench did not finish in time");
        $finish;
    end

endmodule

pe_wave.vcd
$date
	Tue Jul 21 03:26:05 2026
$end
$version
	Icarus Verilog
$end
$timescale
	1ps
$end
$scope module tb_pe $end
$var wire 32 ! psum_out [31:0] $end
$var wire 8 " act_out [7:0] $end
$var parameter 32 # ACC_WIDTH $end
$var parameter 64 $ CLK_PERIOD $end
$var parameter 32 % DATA_WIDTH $end
$var reg 8 & act_in [7:0] $end
$var reg 1 ' clk $end
$var reg 1 ( load_weight $end
$var reg 32 ) psum_in [31:0] $end
$var reg 1 * rst_n $end
$var reg 8 + weight_in [7:0] $end
$var integer 32 , fail_count [31:0] $end
$var integer 32 - pass_count [31:0] $end
$scope module dut $end
$var wire 8 . act_in [7:0] $end
$var wire 8 / act_out [7:0] $end
$var wire 1 ' clk $end
$var wire 1 ( load_weight $end
$var wire 32 0 psum_in [31:0] $end
$var wire 32 1 psum_out [31:0] $end
$var wire 1 * rst_n $end
$var wire 8 2 weight_in [7:0] $end
$var parameter 32 3 ACC_WIDTH $end
$var parameter 32 4 DATA_WIDTH $end
$var reg 8 5 act_reg1 [7:0] $end
$var reg 8 6 act_reg2 [7:0] $end
$var reg 16 7 prod_reg [15:0] $end
$var reg 32 8 psum_out_reg [31:0] $end
$var reg 32 9 psum_reg [31:0] $end
$var reg 8 : weight_reg [7:0] $end
$upscope $end
$scope begin $ivl_for_loop0 $end
$var integer 32 ; i [31:0] $end
$upscope $end
$scope task apply_and_check $end
$upscope $end
$scope task apply_reset $end
$upscope $end
$scope task load_pe_weight $end
$upscope $end
$upscope $end
$enddefinitions $end
$comment Show the parameter values. $end
$dumpall
b1000 4
b100000 3
b1000 %
b1010 $
b100000 #
$end
#0
$dumpvars
b0 ;
bx :
bx 9
bx 8
bx 7
bx 6
bx 5
b0 2
bx 1
b0 0
bx /
b0 .
b0 -
b0 ,
b0 +
0*
b0 )
0(
0'
b0 &
bx "
bx !
$end
#5000
b0 :
b0 9
b0 5
b0 7
b0 "
b0 /
b0 6
b0 !
b0 1
b0 8
1'
#10000
0'
#15000
1'
#20000
0'
#25000
1*
1'
#30000
0'
#35000
1'
#40000
b101 +
b101 2
1(
0'
#45000
b101 :
1'
#50000
b11 &
b11 .
0(
0'
#55000
b11 5
b1111 7
1'
#60000
b0 &
b0 .
0'
#65000
b0 5
b0 7
b11 "
b11 /
b11 6
b1111 !
b1111 1
b1111 8
1'
#70000
b1100100 )
b1100100 0
b100 &
b100 .
b10 -
0'
#75000
b0 "
b0 /
b0 6
b0 !
b0 1
b0 8
b1100100 9
b100 5
b10100 7
1'
#80000
b0 )
b0 0
b0 &
b0 .
0'
#85000
b0 9
b0 5
b0 7
b100 "
b100 /
b100 6
b1111000 !
b1111000 1
b1111000 8
1'
#90000
b11111101 &
b11111101 .
b100 -
0'
#95000
b0 "
b0 /
b0 6
b0 !
b0 1
b0 8
b11111101 5
b1111111111110001 7
1'
#100000
b0 &
b0 .
0'
#105000
b0 5
b0 7
b11111101 "
b11111101 /
b11111101 6
b11111111111111111111111111110001 !
b11111111111111111111111111110001 1
b11111111111111111111111111110001 8
1'
#110000
b110 -
0'
#115000
b0 "
b0 /
b0 6
b0 !
b0 1
b0 8
1'
#120000
b11111001 +
b11111001 2
1(
0'
#125000
b11111001 :
1'
#130000
b110 &
b110 .
0(
0'
#135000
b110 5
b1111111111010110 7
1'
#140000
b0 &
b0 .
0'
#145000
b0 5
b0 7
b110 "
b110 /
b110 6
b11111111111111111111111111010110 !
b11111111111111111111111111010110 1
b11111111111111111111111111010110 8
1'
#150000
b11111010 &
b11111010 .
b1000 -
0'
#155000
b0 "
b0 /
b0 6
b0 !
b0 1
b0 8
b11111010 5
b101010 7
1'
#160000
b0 &
b0 .
0'
#165000
b0 5
b0 7
b11111010 "
b11111010 /
b11111010 6
b101010 !
b101010 1
b101010 8
1'
#170000
b1010 -
0'
#175000
b0 "
b0 /
b0 6
b0 !
b0 1
b0 8
1'
#180000
b10000000 +
b10000000 2
1(
0'
#185000
b10000000 :
1'
#190000
b10000000 &
b10000000 .
0(
0'
#195000
b10000000 5
b100000000000000 7
1'
#200000
b0 &
b0 .
0'
#205000
b0 5
b0 7
b10000000 "
b10000000 /
b10000000 6
b100000000000000 !
b100000000000000 1
b100000000000000 8
1'
#210000
b1100 -
0'
#215000
b0 "
b0 /
b0 6
b0 !
b0 1
b0 8
1'
#220000
b0 +
b0 2
1(
0'
#225000
b0 :
1'
#230000
b111110100 )
b111110100 0
b1111111 &
b1111111 .
0(
0'
#235000
b111110100 9
b1111111 5
1'
#240000
b0 )
b0 0
b0 &
b0 .
0'
#245000
b0 9
b0 5
b1111111 "
b1111111 /
b1111111 6
b111110100 !
b111110100 1
b111110100 8
1'
#250000
b1110 -
0'
#255000
b0 "
b0 /
b0 6
b0 !
b0 1
b0 8
1'
#260000
b1001 +
b1001 2
1(
0'
#265000
b1001 :
1'
#270000
b1001101 )
b1001101 0
0(
0'
#275000
b1001101 9
1'
#280000
b0 )
b0 0
0'
#285000
b0 9
b1001101 !
b1001101 1
b1001101 8
1'
#290000
b10000 -
0'
#295000
b0 !
b0 1
b0 8
1'
#300000
0'
#305000
1'
#310000
0'
#315000
1'
#320000
0'
#325000
1'
#330000
0'
#335000
1'
#340000
b1010 &
b1010 .
0'
#345000
b1010 5
b1011010 7
1'
#350000
b10100 &
b10100 .
b1 ;
0'
#355000
b1010 "
b1010 /
b1010 6
b1011010 !
b1011010 1
b1011010 8
b10100 5
b10110100 7
1'
#360000
b10001 -
b11110 &
b11110 .
b10 ;
0'
#365000
b11110 5
b100001110 7
b10100 "
b10100 /
b10100 6
b10110100 !
b10110100 1
b10110100 8
1'
#370000
b10010 -
b101000 &
b101000 .
b11 ;
0'
#375000
b11110 "
b11110 /
b11110 6
b100001110 !
b100001110 1
b100001110 8
b101000 5
b101101000 7
1'
#380000
b10011 -
b100 ;
0'
#385000
b101000 "
b101000 /
b101000 6
b101101000 !
b101101000 1
b101101000 8
1'
#390000
b10100 -
b101 ;
0'
#395000
1'
#400000
b110 ;
0'
